slh_dsa_botan3/__init__.py
slh_dsa_botan3-0.1.3.dist-info/licenses/LICENSE
slh_dsa_botan3-0.1.3.dist-info/METADATA
slh_dsa_botan3-0.1.3.dist-info/WHEEL
slh_dsa_botan3-0.1.3.dist-info/top_level.txt
slh_dsa_botan3-0.1.3.dist-info/zip-safe
slh_dsa_botan3-0.1.3.dist-info/RECORD
