Metadata-Version: 2.4
Name: slh_dsa_botan3
Version: 0.1.3
Summary: FIPS-205 SLH-DSA bindings for botan3
Home-page: https://gitlab.com/archive-rip/slh_dsa_botan3
Author: the terrible archivist
Author-email: the terrible archivist <info@archive.rip>
License:                     GNU GENERAL PUBLIC LICENSE
Project-URL: Homepage, https://gitlab.com/archive-rip/slh_dsa_botan3
Project-URL: Issues, https://gitlab.com/archive-rip/slh_dsa_botan3/-/issues
Project-URL: Repository, https://gitlab.com/archive-rip/slh_dsa_botan3.git
Project-URL: Documentation, https://archive-rip.gitlab.io/slh_dsa_botan3
Keywords: SLH-DSA,FIPS-205,cryptography,post-quantum,signature,sphincs
Classifier: Development Status :: 4 - Beta
Classifier: Intended Audience :: Developers
Classifier: Programming Language :: Python :: 3 :: Only
Classifier: License :: OSI Approved :: GNU General Public License v3 (GPLv3)
Classifier: Topic :: Security :: Cryptography
Requires-Python: >=3.11
License-File: LICENSE
Requires-Dist: pycryptodome
Provides-Extra: dev
Requires-Dist: black; extra == "dev"
Requires-Dist: isort; extra == "dev"
Requires-Dist: pre-commit; extra == "dev"
Requires-Dist: sphinx; extra == "dev"
Requires-Dist: sphinx-rtd-theme; extra == "dev"
Provides-Extra: test
Requires-Dist: coverage; extra == "test"
Dynamic: author
Dynamic: home-page
Dynamic: license-file
